odoo/addons/pos_mail_receipt/README.rst
odoo/addons/pos_mail_receipt/__init__.py
odoo/addons/pos_mail_receipt/__manifest__.py
odoo/addons/pos_mail_receipt/data/email.xml
odoo/addons/pos_mail_receipt/i18n/fr.po
odoo/addons/pos_mail_receipt/i18n/it.po
odoo/addons/pos_mail_receipt/i18n/pos_mail_receipt.pot
odoo/addons/pos_mail_receipt/models/__init__.py
odoo/addons/pos_mail_receipt/models/pos_order.py
odoo/addons/pos_mail_receipt/readme/CONTRIBUTORS.rst
odoo/addons/pos_mail_receipt/readme/DESCRIPTION.rst
odoo/addons/pos_mail_receipt/readme/USAGE.rst
odoo/addons/pos_mail_receipt/static/description/icon.png
odoo/addons/pos_mail_receipt/static/description/index.html
odoo/addons/pos_mail_receipt/static/src/css/pos.css
odoo/addons/pos_mail_receipt/static/src/css/print.css
odoo/addons/pos_mail_receipt/static/src/js/screens.js
odoo/addons/pos_mail_receipt/static/src/xml/pos.xml
odoo/addons/pos_mail_receipt/templates/assets.xml
odoo/addons/pos_mail_receipt/tests/__init__.py
odoo/addons/pos_mail_receipt/tests/test_module.py
odoo/addons/pos_mail_receipt/views/pos_order_form_mail_receipt_sent.xml
odoo12_addon_pos_mail_receipt-12.0.1.0.0.99.dev15.dist-info/METADATA
odoo12_addon_pos_mail_receipt-12.0.1.0.0.99.dev15.dist-info/WHEEL
odoo12_addon_pos_mail_receipt-12.0.1.0.0.99.dev15.dist-info/top_level.txt
odoo12_addon_pos_mail_receipt-12.0.1.0.0.99.dev15.dist-info/RECORD
